yogi_formula/__init__.py
yogi_formula/fin_formula.py
yogi_formula-0.1.2.dist-info/METADATA
yogi_formula-0.1.2.dist-info/WHEEL
yogi_formula-0.1.2.dist-info/top_level.txt
yogi_formula-0.1.2.dist-info/RECORD
