Metadata-Version: 2.1
Name: yogi-formula
Version: 0.1.2
Summary: My first Python library
Home-page: https://github.com/yogeshnile/fin-formula
Author: Yogesh Nile
Author-email: yogeshnile.work4u@gmail.com
License: MIT
Platform: UNKNOWN
Classifier: Programming Language :: Python :: 3
Classifier: License :: OSI Approved :: MIT License
Classifier: Operating System :: OS Independent
Requires-Python: >=3.6
